benchmarks/__init__.py
benchmarks/benchmarks.py
neuronunit/__init__.py
neuronunit/aibs.py
neuronunit/bbp.py
neuronunit/cellmodelp.py
neuronunit/neuroelectro.py
neuronunit/neuromldb.py
neuronunit/plottools.py
neuronunit/allenapi/__init__.py
neuronunit/allenapi/aibs.py
neuronunit/allenapi/allen_data_driven.py
neuronunit/allenapi/allen_data_efel_features_opt.py
neuronunit/allenapi/make_allen_tests.py
neuronunit/allenapi/make_allen_tests_from_id.py
neuronunit/allenapi/neuroelectroapi.py
neuronunit/allenapi/other_feature_extraction.py
neuronunit/allenapi/utils.py
neuronunit/capabilities/__init__.py
neuronunit/capabilities/channel.py
neuronunit/capabilities/morphology.py
neuronunit/capabilities/spike_functions.py
neuronunit/models/__init__.py
neuronunit/models/channel.py
neuronunit/models/lems.py
neuronunit/models/morphology.py
neuronunit/models/optimization_model_layer.py
neuronunit/models/reduced.py
neuronunit/models/static.py
neuronunit/models/very_reduced.py
neuronunit/models/very_reduced_sans_lems.py
neuronunit/models/backends/__init__.py
neuronunit/models/backends/base.py
neuronunit/models/backends/general_pyNN.py
neuronunit/models/backends/geppetto.py
neuronunit/models/backends/glif.py
neuronunit/models/backends/hhrawf.py
neuronunit/models/backends/jNeuroML.py
neuronunit/models/backends/neuron.py
neuronunit/models/backends/parse_glif.py
neuronunit/models/backends/rawpy.py
neuronunit/models/backends/static.py
neuronunit/neuroconstruct/__init__.py
neuronunit/neuroconstruct/capabilities.py
neuronunit/neuroconstruct/models.py
neuronunit/optimization/__init__.py
neuronunit/optimization/algorithms.py
neuronunit/optimization/data_transport_container.py
neuronunit/optimization/data_transport_container_orig.py
neuronunit/optimization/model_parameters.py
neuronunit/optimization/neuronunit_to_bpo.py
neuronunit/optimization/optimization_management.py
neuronunit/optimization/stoppingCriteria.py
neuronunit/tests/__init__.py
neuronunit/tests/base.py
neuronunit/tests/channel.py
neuronunitopt-0.19.dist-info/METADATA
neuronunitopt-0.19.dist-info/WHEEL
neuronunitopt-0.19.dist-info/top_level.txt
neuronunitopt-0.19.dist-info/RECORD
